MANIFEST.in
readme.rst
requirements.txt
setup.py
jirafs_latex/__init__.py
jirafs_latex/plugin.py
jirafs_latex.egg-info/PKG-INFO
jirafs_latex.egg-info/SOURCES.txt
jirafs_latex.egg-info/dependency_links.txt
jirafs_latex.egg-info/entry_points.txt
jirafs_latex.egg-info/pbr.json
jirafs_latex.egg-info/requires.txt
jirafs_latex.egg-info/top_level.txt