Metadata-Version: 1.1
Name: jirafs-latex
Version: 2.0
Summary: Automatically convert Latex documents into PDFs when uploading to JIRA.
Home-page: https://github.com/coddingtonbear/jirafs-latex
Author: Adam Coddington
Author-email: me@adamcoddington.net
License: UNKNOWN
Platform: UNKNOWN
Classifier: License :: OSI Approved :: MIT License
Classifier: Operating System :: OS Independent
Classifier: Programming Language :: Python :: 3
